diarama_api/__init__.py
diarama_api/auth.py
diarama_api/client.py
diarama_api/files.py
diarama_api/games.py
diarama_api/media.py
diarama_api/payments.py
diarama_api/platforms.py
diarama_api/players.py
diarama_api/roles.py
diarama_api/shop.py
diarama_api-0.1.32.dist-info/METADATA
diarama_api-0.1.32.dist-info/WHEEL
diarama_api-0.1.32.dist-info/top_level.txt
diarama_api-0.1.32.dist-info/RECORD
