Metadata-Version: 2.4
Name: diarama-api
Version: 0.1.32
Summary: Python SDK для работы с API Diarama Studio
Author-email: Haru <hello@chinoharu.ru>
License: MIT
Project-URL: Homepage, https://diaramastudio.ru
Requires-Python: >=3.8
Requires-Dist: requests>=2.25.0
